bmad_pack_installer/__init__.py
bmad_pack_installer/__main__.py
bmad_pack_installer/cli.py
bmad_pack_installer/hash_utils.py
bmad_pack_installer/installer.py
bmad_pack_installer/manifest.py
bmad_pack_installer/py.typed
bmad_pack_installer/symlink.py
bmad_pack_installer/validators.py
bmad_pack_installer-1.1.0.dist-info/METADATA
bmad_pack_installer-1.1.0.dist-info/WHEEL
bmad_pack_installer-1.1.0.dist-info/entry_points.txt
bmad_pack_installer-1.1.0.dist-info/licenses/LICENSE
bmad_pack_installer-1.1.0.dist-info/RECORD
