Metadata-Version: 2.4
Name: bmad-pack-installer
Version: 1.1.0
Summary: Installer for BMAD expansion packs
Project-URL: Homepage, https://github.com/najibninaba/bmad-pack-installer
Project-URL: Repository, https://github.com/najibninaba/bmad-pack-installer
Project-URL: Issues, https://github.com/najibninaba/bmad-pack-installer/issues
Author-email: Najib Ninaba <najibninaba@gmail.com>
License: MIT License
License-File: LICENSE
Classifier: Development Status :: 4 - Beta
Classifier: Intended Audience :: Developers
Classifier: License :: OSI Approved :: MIT License
Classifier: Programming Language :: Python :: 3
Classifier: Programming Language :: Python :: 3.9
Classifier: Programming Language :: Python :: 3.10
Classifier: Programming Language :: Python :: 3.11
Classifier: Programming Language :: Python :: 3.12
Classifier: Topic :: Software Development
Requires-Python: >=3.9
Requires-Dist: click>=8.1.0
Requires-Dist: pyyaml>=6.0
Requires-Dist: rich>=13.0.0
